lora_e220.py
lora_e220_constants.py
lora_e220_operation_constant.py
ebyte_lora_e220_rpi-0.0.2.dist-info/LICENSE.md
ebyte_lora_e220_rpi-0.0.2.dist-info/METADATA
ebyte_lora_e220_rpi-0.0.2.dist-info/WHEEL
ebyte_lora_e220_rpi-0.0.2.dist-info/top_level.txt
ebyte_lora_e220_rpi-0.0.2.dist-info/RECORD
