Metadata-Version: 2.1
Name: ebyte-lora-e220-rpi
Version: 0.0.2
Summary: LoRa EBYTE E220 device library complete and tested with Arduino, esp8266, esp32, STM32 and Raspberry Pi Pico. LLCC68
Home-page: https://github.com/xreef/EByte_LoRa_E220_raspberrypi_library
Author: Renzo Mischianti
Author-email: Renzo Mischianti <renzo@mischianti.org>
Maintainer: Renzo Mischianti
Maintainer-email: Renzo Mischianti <renzo@mischianti.org>
License: The MIT License (MIT)
Project-URL: homepage, https://www.mischianti.org
Project-URL: Documentation, https://www.mischianti.org/category/my-libraries/lora-e220-llcc68-devices/
Project-URL: Documentazione, https://www.mischianti.org/it/category/le-mie-librerie/dispositivi-lora-e220-llcc68/
Project-URL: Repository, https://github.com/xreef/EByte_LoRa_E220_raspberrypi_library
Project-URL: Bug Tracker, https://github.com/xreef/EByte_LoRa_E220_raspberrypi_library/issues
Project-URL: Examples, https://github.com/xreef/EByte_LoRa_E220_raspberrypi_library/tree/master/examples
Keywords: lora,e220,ebyte,llcc68,raspberrypi,esp32,esp8266,arduino,pico,stm32,SAMD,UART,EByte
Classifier: Development Status :: 5 - Production/Stable
Classifier: Programming Language :: Python :: 3
Classifier: License :: OSI Approved :: MIT License
Requires-Python: >=3.7
License-File: LICENSE.md
